<DOMSymbolItem xmlns:xsi="http://www.w3.org/2001/XMLSchema-instance" xmlns="http://ns.adobe.com/xfl/2008/" name="meteor asset" itemID="582f1664-00000775" lastModified="1479829159">
  <timeline>
    <DOMTimeline name="meteor asset">
      <layers>
        <DOMLayer name="Layer 1" color="#4F80FF" current="true" isSelected="true">
          <frames>
            <DOMFrame index="0" keyMode="9728">
              <elements>
                <DOMGroup selected="true">
                  <matrix>
                    <Matrix a="0.681915283203125" d="0.682144165039062"/>
                  </matrix>
                  <members>
                    <DOMShape selected="true" isDrawingObject="true">
                      <matrix>
                        <Matrix a="0.0478668212890625" b="0.0386810302734375" c="-0.0386810302734375" d="0.0478668212890625" tx="30.85" ty="-47"/>
                      </matrix>
                      <fills>
                        <FillStyle index="1">
                          <SolidColor color="#ED1C24"/>
                        </FillStyle>
                      </fills>
                      <edges>
                        <Edge fillStyle1="1" edges="!9787 4008|3580 6370!3580 6370[3734 5892 3772 5787!3772 5787[3891 5453 4020 5205!4020 5205[4359 4556 4953 4147!4953 4147[5683 3645 6906 3412!6906 3412[8300 3147 10409 3214!10409 3214|9787 4008"/>
                        <Edge cubics="!9787 4008(;9787,4008 3580,6370 3580,6370p9787 4008q3580 6370);"/>
                        <Edge cubics="!3580 6370(3580,6370;4074,4840 4470,3024 10409,3214q3580 6370Q3734 5892q3772 5787Q3891 5453q4020 5205Q4359 4556q4953 4147Q5683 3645q6906 3412Q8300 3147q10409 3214);"/>
                        <Edge cubics="!10409 3214(10409,3214;10409,3214 9787,4008 9787,4008q10409 3214p9787 4008)9787,4008;"/>
                      </edges>
                    </DOMShape>
                    <DOMGroup selected="true">
                      <matrix>
                        <Matrix a="0.681915283203125" d="0.682144165039062"/>
                      </matrix>
                      <members>
                        <DOMShape selected="true" isDrawingObject="true">
                          <matrix>
                            <Matrix a="0.0478668212890625" b="0.0386810302734375" c="-0.0386810302734375" d="0.0478668212890625" tx="30.85" ty="-47"/>
                          </matrix>
                          <fills>
                            <FillStyle index="1">
                              <LinearGradient>
                                <matrix>
                                  <Matrix a="-0.126434326171875" b="-0.1417236328125" c="0.16912841796875" d="-0.15087890625" tx="863.75" ty="175.4"/>
                                </matrix>
                                <GradientEntry color="#FFFFFF" ratio="0"/>
                                <GradientEntry color="#FFF200" ratio="0.482352941176471"/>
                                <GradientEntry color="#ED1C24" ratio="1"/>
                              </LinearGradient>
                            </FillStyle>
                          </fills>
                          <edges>
                            <Edge fillStyle1="1" edges="!15542 6169[15503 6169 15462 6163!15462 6163[15286 6134 15171 5998!15171 5998[15056 5862 15056 5684!15056 5684|15055 5513!15055 5513[15054 4958 15085 4669!15085 4669[15129 4269 15261 3965!15261 3965[15408 3626 15703 3310!15703 3310[16011
 2982 16535 2617!16535 2617[16674 2519 16873 2390!16873 2390|17329 2099!17329 2099[17969 1693 18176 1537!18176 1537[18510 1286 18510 1153!18510 1153[18510 979 18620 845!18620 845[18731 711 18901 677!18901 677[18949 668 18996 668!18996
 668[19142 668 19264 749!19264 749[19387 831 19444 968!19444 968[19977 2262 19214 3244!19214 3244[18922 3620 18412 3987!18412 3987[18112 4203 17506 4562!17506 4562[16842 4956 16568 5167!16568 5167[16110 5519 16001 5840!16001 5840[15950
 5989 15823 6080!15823 6080[15696 6169 15542 6169"/>
                            <Edge cubics="!15542 6169(;15515,6169 15489,6167 15462,6163q15542 6169Q15503 6169q15462 6163)15462,6163;"/>
                            <Edge cubics="!15462 6163(;15227,6124 15056,5921 15056,5684q15462 6163Q15286 6134q15171 5998Q15056 5862q15056 5684)15056,5684;"/>
                            <Edge cubics="!15056 5684(15056,5684;15056,5684 15055,5513 15055,5513p15056 5684q15055 5513)15055,5513;"/>
                            <Edge cubics="!15055 5513(;15052,4256 15113,3607 16535,2617q15055 5513Q15054 4958q15085 4669Q15129 4269q15261 3965Q15408 3626q15703 3310Q16011 2982q16535 2617);"/>
                            <Edge cubics="!16535 2617(;16637,2545 16751,2469 16873,2390q16535 2617Q16674 2519q16873 2390);"/>
                            <Edge cubics="!16873 2390(;17036,2285 17188,2189 17329,2099q16873 2390 17329 2099);"/>
                            <Edge cubics="!17329 2099(;18014,1664 18510,1350 18510,1153q17329 2099Q17969 1693q18176 1537Q18510 1286q18510 1153);"/>
                            <Edge cubics="!18510 1153(;18510,921 18674,722 18901,677q18510 1153Q18510 979q18620 845Q18731 711q18901 677);"/>
                            <Edge cubics="!18901 677(;18933,671 18964,668 18996,668q18901 677Q18949 668q18996 668);"/>
                            <Edge cubics="!18996 668(18996,668;19189,668 19368,784 19444,968q18996 668Q19142 668q19264 749Q19387 831q19444 968)19444,968;"/>
                            <Edge cubics="!19444 968(19444,968;20254,2933 18666,3875 17506,4562q19444 968Q19977 2262q19214 3244Q18922 3620q18412 3987Q18112 4203q17506 4562)17506,4562;"/>
                            <Edge cubics="!17506 4562(17506,4562;16847,4953 16165,5358 16001,5840q17506 4562Q16842 4956q16568 5167Q16110 5519q16001 5840)16001,5840;"/>
                            <Edge cubics="!16001 5840(16001,5840;15933,6040 15746,6169 15542,6169q16001 5840Q15950 5989q15823 6080Q15696 6169q15542 6169)15542,6169;"/>
                          </edges>
                        </DOMShape>
                        <DOMShape selected="true" isDrawingObject="true">
                          <matrix>
                            <Matrix a="0.0478668212890625" b="0.0386810302734375" c="-0.0386810302734375" d="0.0478668212890625" tx="30.85" ty="-47"/>
                          </matrix>
                          <fills>
                            <FillStyle index="1">
                              <SolidColor color="#ED1C24"/>
                            </FillStyle>
                          </fills>
                          <edges>
                            <Edge fillStyle0="1" edges="
!18996 182[18899 182 18807 201!18807 201[18499 262 18285 492!18285 492[18072 721 18032 1028!18032 1028[17933 1125 17638 1322!17638 1322[17472 1433 17068 1690!17068 1690[16636 1966 16611 1982!16611 1982[16418 2106 16256 2219!16256 2219
[15673 2626 15329 3002!15329 3002[14984 3379 14803 3806!14803 3806[14645 4181 14597 4638!14597 4638[14568 4920 14570 5514!14570 5514|14570 5684!14570 5684[14570 6040 14801 6312!14801 6312[15031 6583 15383 6642!15383 6642[15469 6655 15542
 6655!15542 6655[15851 6655 16104 6475!16104 6475[16360 6294 16461 5996!16461 5996[16531 5790 16949 5488!16949 5488[17196 5310 17754 4980!17754 4980[18416 4588 18730 4361!18730 4361[19252 3985 19572 3583!19572 3583[20048 2983 20130 2270
!20130 2270[20212 1557 19893 783!19893 783[19780 508 19533 344!19533 344[19288 182 18996 182!18995 1153[19361 2039 18986 2719!18986 2719[18703 3232 17882 3765!17882 3765[17690 3889 17165 4201!17165 4201[16709 4472 16471 4637!16471 4637
[15721 5156 15541 5684!15541 5684[15541 5047 15551 4883!15551 4883[15575 4505 15674 4242!15674 4242[15789 3937 16049 3654!16049 3654[16320 3359 16813 3015!16813 3015[16948 2920 17136 2798!17136 2798[17450 2596 17956 2275!17956 2275[18343
 2025 18536 1872!18536 1872[18774 1684 18881 1521!18881 1521[18995 1347 18995 1153"/>
                            <Edge cubics="!18996 182(;18933,182 18870,188 18807,201q18996 182Q18899 182q18807 201);"/>
                            <Edge cubics="!18807 201(18807,201;18394,283 18085,620 18032,1028q18807 201Q18499 262q18285 492Q18072 721q18032 1028)18032,1028;"/>
                            <Edge cubics="!18032 1028(;17882,1174 17452,1446 17068,1690q18032 1028Q17933 1125q17638 1322Q17472 1433q17068 1690);"/>
                            <Edge cubics="!17068 1690(17068,1690;16927,1780 16774,1876 16611,1982q17068 1690Q16636 1966q16611 1982)16611,1982;"/>
                            <Edge cubics="!16611 1982(;16485,2063 16365,2143 16256,2219q16611 1982Q16418 2106q16256 2219);"/>
                            <Edge cubics="!16256 2219(16256,2219;15479,2761 15044,3236 14803,3806q16256 2219Q15673 2626q15329 3002Q14984 3379q14803 3806)14803,3806;"/>
                            <Edge cubics="!14803 3806(;14567,4364 14568,4897 14570,5514q14803 3806Q14645 4181q14597 4638Q14568 4920q14570 5514);"/>
                            <Edge cubics="!14570 5514(;14570,5569 14570,5626 14570,5684q14570 5514 14570 5684);"/>
                            <Edge cubics="!14570 5684(14570,5684;14570,6159 14914,6564 15383,6642q14570 5684Q14570 6040q14801 6312Q15031 6583q15383 6642)15383,6642;"/>
                            <Edge cubics="!15383 6642(;15436,6650 15489,6655 15542,6655q15383 6642Q15469 6655q15542 6655);"/>
                            <Edge cubics="!15542 6655(;15952,6655 16325,6395 16461,5996q15542 6655Q15851 6655q16104 6475Q16360 6294q16461 5996);"/>
                            <Edge cubics="!16461 5996(;16567,5684 17225,5293 17754,4980q16461 5996Q16531 5790q16949 5488Q17196 5310q17754 4980);"/>
                            <Edge cubics="!17754 4980(;18412,4590 19092,4186 19572,3583q17754 4980Q18416 4588q18730 4361Q19252 3985q19572 3583);"/>
                            <Edge cubics="!19572 3583(;20207,2783 20318,1815 19893,783q19572 3583Q20048 2983q20130 2270Q20212 1557q19893 783);"/>
                            <Edge cubics="!19893 783(;19741,414 19383,182 18996,182q19893 783Q19780 508q19533 344Q19288 182q18996 182);"/>
                            <Edge cubics="!18995 1153(;20063,3743 16109,4017 15541,5684q18995 1153Q19361 2039q18986 2719Q18703 3232q17882 3765Q17690 3889q17165 4201Q16709 4472q16471 4637Q15721 5156q15541 5684);"/>
                            <Edge cubics="!15541 5684(;15541,4462 15472,3949 16813,3015q15541 5684Q15541 5047q15551 4883Q15575 4505q15674 4242Q15789 3937q16049 3654Q16320 3359q16813 3015);"/>
                            <Edge cubics="!16813 3015(;16912,2945 17020,2873 17136,2798q16813 3015Q16948 2920q17136 2798);"/>
                            <Edge cubics="!17136 2798(;18391,1990 18995,1685 18995,1153q17136 2798Q17450 2596q17956 2275Q18343 2025q18536 1872Q18774 1684q18881 1521Q18995 1347q18995 1153);"/>
                          </edges>
                        </DOMShape>
                      </members>
                    </DOMGroup>
                    <DOMShape selected="true" isDrawingObject="true">
                      <matrix>
                        <Matrix a="0.0478668212890625" b="0.0386810302734375" c="-0.0386810302734375" d="0.0478668212890625" tx="30.85" ty="-47"/>
                      </matrix>
                      <strokes>
                        <StrokeStyle index="1">
                          <SolidStroke scaleMode="normal" caps="none" weight="24.3" joints="miter" miterLimit="4">
                            <fill>
                              <SolidColor color="#ED1C24"/>
                            </fill>
                          </SolidStroke>
                        </StrokeStyle>
                      </strokes>
                      <edges>
                        <Edge strokeStyle="1" edges="
!8622 4684[10326 4684 11883 5342!11883 5342[13387 5978 14546 7138!14546 7138[15706 8297 16342 9801!16342 9801[17000 11357 17000 13062!17000 13062[17000 14767 16342 16324!16342 16324[15706 17827 14546 18987!14546 18987[13387 20147 11883
 20783!11883 20783[10327 21441 8622 21441!8622 21441[6917 21441 5361 20783!5361 20783[3857 20147 2697 18987!2697 18987[1538 17827 902 16324!902 16324[243 14767 243 13062!243 13062[243 11358 902 9801!902 9801[1538 8298 2697 7138!2697 7138
[3857 5978 5361 5342!5361 5342[6917 4684 8622 4684"/>
                        <Edge cubics="!8622 4684(;13249,4684 17000,8435 17000,13062q8622 4684Q10326 4684q11883 5342Q13387 5978q14546 7138Q15706 8297q16342 9801Q17000 11357q17000 13062);"/>
                        <Edge cubics="!17000 13062(;17000,17690 13249,21441 8622,21441q17000 13062Q17000 14767q16342 16324Q15706 17827q14546 18987Q13387 20147q11883 20783Q10327 21441q8622 21441);"/>
                        <Edge cubics="!8622 21441(;3995,21441 243,17690 243,13062q8622 21441Q6917 21441q5361 20783Q3857 20147q2697 18987Q1538 17827q902 16324Q243 14767q243 13062)243,13062;"/>
                        <Edge cubics="!243 13062(;243,8435 3995,4684 8622,4684q243 13062Q243 11358q902 9801Q1538 8298q2697 7138Q3857 5978q5361 5342Q6917 4684q8622 4684)8622,4684;"/>
                      </edges>
                    </DOMShape>
                    <DOMGroup selected="true">
                      <matrix>
                        <Matrix a="0.681915283203125" d="0.682144165039062"/>
                      </matrix>
                      <members>
                        <DOMShape selected="true" isDrawingObject="true">
                          <matrix>
                            <Matrix a="0.0478668212890625" b="0.0386810302734375" c="-0.0386810302734375" d="0.0478668212890625" tx="30.85" ty="-47"/>
                          </matrix>
                          <fills>
                            <FillStyle index="1">
                              <SolidColor color="#FFFFFF"/>
                            </FillStyle>
                          </fills>
                          <edges>
                            <Edge fillStyle1="1" edges="
!9184 20794[8720 20794 8252 20737!8252 20737[7539 20730 6720 20534!6720 20534[5747 20301 4880 19853!4880 19853[3858 19324 3094 18549!3094 18549[2213 17656 1721 16479!1721 16479[1074 14929 999 13496!999 13496[924 12061 1423 10770!1423
 10770[1807 9777 2519 8898!2519 8898[3231 8020 4257 7273!4257 7273[5128 6640 6249 6305!6249 6305[6897 6110 8022 5939!8022 5939[8474 5870 8673 5829!8673 5829[9009 5760 9116 5688!9116 5688[9200 5632 9354 5334!9354 5334[9441 5165 9613 4785
!9613 4785[9982 3966 10253 3516!10253 3516[10720 2740 11322 2199!11322 2199[12939 746 15780 746!15780 746[16052 746 16261 922!16261 922[16469 1099 16514 1367!16514 1367[16559 1636 16420 1871!16420 1871[16281 2106 16023 2195!16023 2195
[15055 2530 14836 2920!14836 2920[14749 3076 14725 3355!14725 3355[14709 3530 14712 3954!14712 3954[14715 4404 14703 4661!14703 4661[14681 5104 14607 5496!14607 5496[14398 6603 13839 7642!13839 7642[15676 7041 16708 6417!16708 6417[18165
 5535 18673 4309!18673 4309[18761 4098 18951 3973!18951 3973[19138 3850 19361 3850!19361 3850[19469 3850 19572 3881!19572 3881[19846 3962 19995 4205!19995 4205[20145 4448 20094 4729!20094 4729[19935 5593 19722 6282!19722 6282[19458 7133
 19074 7854!19074 7854[18152 9583 16409 10788!16409 10788|16437 10788!16437 10788[16595 10788 16785 10812!16785 10812[16899 10827 17119 10865!17119 10865|17151 10870!17151 10870[17331 10901 17426 10913!17426 10913[17568 10931 17676 10931
!17676 10931[17865 10931 18012 10876!18012 10876[18209 10801 18403 10607!18403 10607[18509 10501 18647 10445!18647 10445[18783 10389 18930 10389!18930 10389[19081 10389 19215 10446!19215 10446[19424 10532 19549 10720!19549 10720[19675
 10908 19675 11134!19675 11134[19675 12053 19046 12718!19046 12718[18799 12979 18422 13239!18422 13239[18197 13393 17735 13666!17735 13666[17297 13925 17083 14068!17083 14068[16726 14306 16472 14543!16472 14543[15833 15140 15584 15984
!15584 15984[15262 17075 14649 17973!14649 17973[14036 18871 13179 19509!13179 19509[12331 20140 11314 20467!11314 20467[10297 20795 9184 20795!9184 20795|9184 20794"/>
                            <Edge cubics="!9184 20794(;8877,20794 8564,20775 8252,20737q9184 20794Q8720 20794q8252 20737);"/>
                            <Edge cubics="!8252 20737(;6574,20720 3116,19815 1721,16479q8252 20737Q7539 20730q6720 20534Q5747 20301q4880 19853Q3858 19324q3094 18549Q2213 17656q1721 16479);"/>
                            <Edge cubics="!1721 16479(;858,14413 757,12492 1423,10770q1721 16479Q1074 14929q999 13496Q924 12061q1423 10770);"/>
                            <Edge cubics="!1423 10770(;1935,9445 2889,8269 4257,7273q1423 10770Q1807 9777q2519 8898Q3231 8020q4257 7273);"/>
                            <Edge cubics="!4257 7273(;5579,6312 6991,6096 8022,5939q4257 7273Q5128 6640q6249 6305Q6897 6110q8022 5939);"/>
                            <Edge cubics="!8022 5939(;8459,5872 8955,5796 9116,5688q8022 5939Q8474 5870q8673 5829Q9009 5760q9116 5688);"/>
                            <Edge cubics="!9116 5688(;9244,5603 9457,5130 9613,4785q9116 5688Q9200 5632q9354 5334Q9441 5165q9613 4785);"/>
                            <Edge cubics="!9613 4785(;10294,3274 11434,746 15780,746q9613 4785Q9982 3966q10253 3516Q10720 2740q11322 2199Q12939 746q15780 746);"/>
                            <Edge cubics="!15780 746(;16143,746 16454,1009 16514,1367q15780 746Q16052 746q16261 922Q16469 1099q16514 1367)16514,1367;"/>
                            <Edge cubics="!16514 1367(;16574,1726 16367,2076 16023,2195q16514 1367Q16559 1636q16420 1871Q16281 2106q16023 2195);"/>
                            <Edge cubics="!16023 2195(;15372,2420 14983,2658 14836,2920q16023 2195Q15055 2530q14836 2920);"/>
                            <Edge cubics="!14836 2920(;14707,3151 14709,3505 14712,3954q14836 2920Q14749 3076q14725 3355Q14709 3530q14712 3954);"/>
                            <Edge cubics="!14712 3954(;14715,4377 14719,4903 14607,5496q14712 3954Q14715 4404q14703 4661Q14681 5104q14607 5496);"/>
                            <Edge cubics="!14607 5496(;14458,6286 14177,7014 13839,7642q14607 5496Q14398 6603q13839 7642);"/>
                            <Edge cubics="!13839 7642(;15798,7001 17920,6126 18673,4309q13839 7642Q15676 7041q16708 6417Q18165 5535q18673 4309);"/>
                            <Edge cubics="!18673 4309(;18791,4025 19067,3850 19361,3850q18673 4309Q18761 4098q18951 3973Q19138 3850q19361 3850);"/>
                            <Edge cubics="!19361 3850(;19431,3850 19502,3860 19572,3881q19361 3850Q19469 3850q19572 3881);"/>
                            <Edge cubics="!19572 3881(;19937,3989 20162,4355 20094,4729q19572 3881Q19846 3962q19995 4205Q20145 4448q20094 4729);"/>
                            <Edge cubics="!20094 4729(;19721,6757 18974,9015 16409,10788q20094 4729Q19935 5593q19722 6282Q19458 7133q19074 7854Q18152 9583q16409 10788);"/>
                            <Edge cubics="!16409 10788(;16418,10788 16427,10788 16437,10788q16409 10788p16437 10788);"/>
                            <Edge cubics="!16437 10788(;16674,10788 16900,10827 17119,10865q16437 10788Q16595 10788q16785 10812Q16899 10827q17119 10865);"/>
                            <Edge cubics="!17119 10865(;17119,10865 17151,10870 17151,10870q17119 10865 17151 10870);"/>
                            <Edge cubics="!17151 10870(;17344,10903 17516,10931 17676,10931q17151 10870Q17331 10901q17426 10913Q17568 10931q17676 10931);"/>
                            <Edge cubics="!17676 10931(;17886,10931 18119,10891 18403,10607q17676 10931Q17865 10931q18012 10876Q18209 10801q18403 10607);"/>
                            <Edge cubics="!18403 10607(;18546,10465 18736,10389 18930,10389q18403 10607Q18509 10501q18647 10445Q18783 10389q18930 10389);"/>
                            <Edge cubics="!18930 10389(;19026,10389 19123,10407 19215,10446q18930 10389Q19081 10389q19215 10446);"/>
                            <Edge cubics="!19215 10446(;19493,10561 19675,10833 19675,11134q19215 10446Q19424 10532q19549 10720Q19675 10908q19675 11134);"/>
                            <Edge cubics="!19675 11134(;19675,12520 18644,13129 17735,13666q19675 11134Q19675 12053q19046 12718Q18799 12979q18422 13239Q18197 13393q17735 13666);"/>
                            <Edge cubics="!17735 13666(;16861,14182 15958,14716 15584,15984q17735 13666Q17297 13925q17083 14068Q16726 14306q16472 14543Q15833 15140q15584 15984);"/>
                            <Edge cubics="!15584 15984(;15154,17439 14322,18658 13179,19509q15584 15984Q15262 17075q14649 17973Q14036 18871q13179 19509);"/>
                            <Edge cubics="!13179 19509(;12049,20350 10668,20795 9184,20795q13179 19509Q12331 20140q11314 20467Q10297 20795q9184 20795);"/>
                            <Edge cubics="!9184 20795(;9184,20795 9184,20794 9184,20794q9184 20795 9184 20794);"/>
                          </edges>
                        </DOMShape>
                        <DOMShape selected="true" isDrawingObject="true">
                          <matrix>
                            <Matrix a="0.0478668212890625" b="0.0386810302734375" c="-0.0386810302734375" d="0.0478668212890625" tx="30.85" ty="-47"/>
                          </matrix>
                          <fills>
                            <FillStyle index="1">
                              <SolidColor color="#ED1C24"/>
                            </FillStyle>
                          </fills>
                          <edges>
                            <Edge fillStyle0="1" edges="
!15779 0[14234 0 12995 409!12995 409[11755 818 10843 1629!10843 1629[10156 2241 9634 3098!9634 3098[9333 3593 8934 4477!8934 4477[8736 4917 8651 5070!8651 5070[8463 5117 7909 5201!7909 5201[6731 5382 6023 5595!6023 5595[4783 5969 3819
 6670!3819 6670[2704 7481 1928 8443!1928 8443[1152 9404 728 10500!728 10500[175 11931 252 13504!252 13504[329 15077 1034 16765!1034 16765[1543 17983 2446 18942!2446 18942[3349 19902 4578 20531!4578 20531[5424 20964 6382 21215!6382 21215
[7340 21466 8203 21480!8203 21480[8691 21538 9184 21538!9184 21538[10418 21538 11548 21173!11548 21173[12679 20808 13623 20105!13623 20105[14579 19394 15260 18398!15260 18398[15941 17402 16298 16194!16298 16194[16489 15549 16956 15107
!16956 15107[17162 14912 17470 14705!17470 14705[17692 14555 18113 14306!18113 14306[18601 14017 18840 13855!18840 13855[19239 13582 19520 13298!19520 13298[19968 12847 20193 12302!20193 12302[20419 11759 20419 11132!20419 11132[20419
 10680 20168 10305!20168 10305[19918 9929 19500 9756!19500 9756[19226 9643 18930 9643!18930 9643[18848 9643 18765 9652!18765 9652[19072 9279 19340 8868!19340 8868[19875 8044 20238 7068!20238 7068[20601 6089 20826 4863!20826 4863[20930
 4301 20630 3814!20630 3814[20331 3327 19783 3165!19783 3165[19575 3104 19361 3104!19361 3104[18915 3104 18541 3350!18541 3350[18160 3601 17985 4023!17985 4023[17670 4782 16878 5397!16878 5397[16214 5912 15166 6359!15166 6359[15272 5991
 15339 5632!15339 5632[15422 5194 15446 4712!15446 4712[15460 4432 15457 3948!15457 3948[15455 3694 15458 3566!15458 3566[15464 3352 15486 3285!15486 3285[15537 3230 15668 3156!15668 3156[15893 3027 16267 2897!16267 2897[16782 2719 17061
 2250!17061 2250[17339 1781 17249 1243!17249 1243[17158 705 16742 352!16742 352[16325 0 15780 0!15780 0|15779 0!15779 1490[14886 1799 14468 2197!14468 2197[14110 2538 14015 3043!14015 3043[13977 3246 13969 3534!13969 3534[13966 3643 13968
 4079!13968 4079[13972 4844 13875 5357!13875 5357[13628 6668 12853 7844!12853 7844[12541 8318 12197 8679!12197 8679[11883 9009 11633 9153!11633 9153[11977 9017 12526 8839!12526 8839[12851 8734 13563 8512!13563 8512[14972 8066 15824 7696
!15824 7696[17095 7145 17922 6470!17922 6470[18922 5653 19361 4594!19361 4594[19175 5607 18897 6397!18897 6397[18576 7311 18091 8056!18091 8056[16997 9739 14845 10857!14845 10857[13931 11332 13444 12001!13444 12001[12967 12655 12967 13399
!12967 13399[13037 12981 13247 12686!13247 12686[13461 12383 13850 12168!13850 12168[14581 11763 16285 11541!16285 11541[16359 11532 16437 11532!16437 11532[16557 11532 16722 11554!16722 11554[16797 11565 17025 11603!17025 11603[17225
 11638 17344 11653!17344 11653[17525 11675 17676 11675!17676 11675[18010 11675 18293 11565!18293 11565[18630 11433 18930 11133!18930 11133[18930 11805 18418 12293!18418 12293[18213 12489 17876 12708!17876 12708[17735 12799 17227 13100
!17227 13100[16799 13354 16538 13537!16538 13537[16157 13803 15873 14083!15873 14083[15161 14785 14870 15772!14870 15772[14578 16760 14025 17565!14025 17565[13485 18352 12734 18911!12734 18911[11988 19466 11090 19756!11090 19756[10181
 20049 9184 20049!9184 20049[8745 20049 8300 19991!8300 19991[7665 19991 6920 19815!6920 19815[6043 19608 5257 19205!5257 19205[4332 18732 3642 18038!3642 18038[2847 17239 2409 16190!2409 16190[1223 13353 2118 11038!2118 11038[2811 9245
 4695 7875!4695 7875[5339 7406 6139 7122!6139 7122[6734 6911 7527 6771!7527 6771[7964 6694 8708 6580!8708 6580[9281 6473 9530 6307!9530 6307[9719 6181 9897 5888!9897 5888[10025 5679 10223 5243!10223 5243[10499 4634 10587 4458!10587 4458
[10823 3983 11069 3621!11069 3621[11728 2654 12707 2139!12707 2139[13942 1490 15779 1490"/>
                            <Edge cubics="!15779 0(;13719,0 12059,548 10843,1629q15779 0Q14234 0q12995 409Q11755 818q10843 1629);"/>
                            <Edge cubics="!10843 1629(;9799,2558 9299,3667 8934,4477q10843 1629Q10156 2241q9634 3098Q9333 3593q8934 4477);"/>
                            <Edge cubics="!8934 4477(;8846,4673 8732,4925 8651,5070q8934 4477Q8736 4917q8651 5070);"/>
                            <Edge cubics="!8651 5070(;8471,5115 8153,5164 7909,5201q8651 5070Q8463 5117q7909 5201);"/>
                            <Edge cubics="!7909 5201(;6865,5361 5288,5602 3819,6670q7909 5201Q6731 5382q6023 5595Q4783 5969q3819 6670);"/>
                            <Edge cubics="!3819 6670(;2333,7751 1293,9039 728,10500q3819 6670Q2704 7481q1928 8443Q1152 9404q728 10500);"/>
                            <Edge cubics="!728 10500(;-9,12408 94,14515 1034,16765q728 10500Q175 11931q252 13504Q329 15077q1034 16765);"/>
                            <Edge cubics="!1034 16765(;1713,18389 2939,19692 4578,20531q1034 16765Q1543 17983q2446 18942Q3349 19902q4578 20531);"/>
                            <Edge cubics="!4578 20531(;5706,21109 7053,21461 8203,21480q4578 20531Q5424 20964q6382 21215Q7340 21466q8203 21480);"/>
                            <Edge cubics="!8203 21480(;8531,21519 8860,21538 9184,21538q8203 21480Q8691 21538q9184 21538);"/>
                            <Edge cubics="!9184 21538(;10829,21538 12364,21043 13623,20105q9184 21538Q10418 21538q11548 21173Q12679 20808q13623 20105);"/>
                            <Edge cubics="!13623 20105(;14897,19157 15822,17805 16298,16194q13623 20105Q14579 19394q15260 18398Q15941 17402q16298 16194);"/>
                            <Edge cubics="!16298 16194(;16576,15254 17169,14865 18113,14306q16298 16194Q16489 15549q16956 15107Q17162 14912q17470 14705Q17692 14555q18113 14306);"/>
                            <Edge cubics="!18113 14306(;18597,14020 19098,13724 19520,13298q18113 14306Q18601 14017q18840 13855Q19239 13582q19520 13298);"/>
                            <Edge cubics="!19520 13298(;20117,12696 20419,11967 20419,11132q19520 13298Q19968 12847q20193 12302Q20419 11759q20419 11132);"/>
                            <Edge cubics="!20419 11132(;20419,10530 20057,9987 19500,9756q20419 11132Q20419 10680q20168 10305Q19918 9929q19500 9756);"/>
                            <Edge cubics="!19500 9756(;19316,9680 19122,9643 18930,9643q19500 9756Q19226 9643q18930 9643);"/>
                            <Edge cubics="!18930 9643(;18875,9643 18820,9646 18765,9652q18930 9643Q18848 9643q18765 9652);"/>
                            <Edge cubics="!18765 9652(;18972,9401 19163,9140 19340,8868q18765 9652Q19072 9279q19340 8868);"/>
                            <Edge cubics="!19340 8868(;20053,7771 20526,6499 20826,4863q19340 8868Q19875 8044q20238 7068Q20601 6089q20826 4863);"/>
                            <Edge cubics="!20826 4863(;20964,4114 20514,3381 19783,3165q20826 4863Q20930 4301q20630 3814Q20331 3327q19783 3165);"/>
                            <Edge cubics="!19783 3165(;19643,3124 19501,3104 19361,3104q19783 3165Q19575 3104q19361 3104);"/>
                            <Edge cubics="!19361 3104(;18773,3104 18221,3454 17985,4023q19361 3104Q18915 3104q18541 3350Q18160 3601q17985 4023);"/>
                            <Edge cubics="!17985 4023(;17535,5108 16422,5823 15166,6359q17985 4023Q17670 4782q16878 5397Q16214 5912q15166 6359);"/>
                            <Edge cubics="!15166 6359(;15233,6127 15292,5885 15339,5632q15166 6359Q15272 5991q15339 5632);"/>
                            <Edge cubics="!15339 5632(;15464,4969 15460,4403 15457,3948q15339 5632Q15422 5194q15446 4712Q15460 4432q15457 3948);"/>
                            <Edge cubics="!15457 3948(;15455,3710 15453,3387 15486,3285q15457 3948Q15455 3694q15458 3566Q15464 3352q15486 3285);"/>
                            <Edge cubics="!15486 3285(;15515,3254 15682,3100 16267,2897q15486 3285Q15537 3230q15668 3156Q15893 3027q16267 2897);"/>
                            <Edge cubics="!16267 2897(;16954,2659 17369,1960 17249,1243q16267 2897Q16782 2719q17061 2250Q17339 1781q17249 1243);"/>
                            <Edge cubics="!17249 1243(;17128,525 16507,0 15780,0q17249 1243Q17158 705q16742 352Q16325 0q15780 0);"/>
                            <Edge cubics="!15780 0(;15780,0 15779,0 15779,0q15780 0 15779 0);"/>
                            <Edge cubics="!15779 1490(;13258,2363 14231,3468 13875,5357q15779 1490Q14886 1799q14468 2197Q14110 2538q14015 3043Q13977 3246q13969 3534Q13966 3643q13968 4079Q13972 4844q13875 5357);"/>
                            <Edge cubics="!13875 5357(;13511,7289 12262,8791 11633,9153q13875 5357Q13628 6668q12853 7844Q12541 8318q12197 8679Q11883 9009q11633 9153);"/>
                            <Edge cubics="!11633 9153(;13767,8308 18100,7633 19361,4594q11633 9153Q11977 9017q12526 8839Q12851 8734q13563 8512Q14972 8066q15824 7696Q17095 7145q17922 6470Q18922 5653q19361 4594);"/>
                            <Edge cubics="!19361 4594(;18903,7083 17938,9250 14845,10857q19361 4594Q19175 5607q18897 6397Q18576 7311q18091 8056Q16997 9739q14845 10857);"/>
                            <Edge cubics="!14845 10857(14845,10857;13612,11498 12967,12418 12967,13399q14845 10857Q13931 11332q13444 12001Q12967 12655q12967 13399);"/>
                            <Edge cubics="!12967 13399(;13152,12299 14031,11835 16285,11541q12967 13399Q13037 12981q13247 12686Q13461 12383q13850 12168Q14581 11763q16285 11541);"/>
                            <Edge cubics="!16285 11541(;16334,11535 16385,11532 16437,11532q16285 11541Q16359 11532q16437 11532);"/>
                            <Edge cubics="!16437 11532(;16620,11532 16817,11568 17025,11603q16437 11532Q16557 11532q16722 11554Q16797 11565q17025 11603);"/>
                            <Edge cubics="!17025 11603(;17232,11639 17451,11675 17676,11675q17025 11603Q17225 11638q17344 11653Q17525 11675q17676 11675);"/>
                            <Edge cubics="!17676 11675(;18077,11675 18502,11561 18930,11133q17676 11675Q18010 11675q18293 11565Q18630 11433q18930 11133);"/>
                            <Edge cubics="!18930 11133(;18930,13151 15743,12815 14870,15772q18930 11133Q18930 11805q18418 12293Q18213 12489q17876 12708Q17735 12799q17227 13100Q16799 13354q16538 13537Q16157 13803q15873 14083Q15161 14785q14870 15772);"/>
                            <Edge cubics="!14870 15772(;14081,18439 11858,20049 9184,20049q14870 15772Q14578 16760q14025 17565Q13485 18352q12734 18911Q11988 19466q11090 19756Q10181 20049q9184 20049);"/>
                            <Edge cubics="!9184 20049(;8894,20049 8599,20030 8300,19991q9184 20049Q8745 20049q8300 19991);"/>
                            <Edge cubics="!8300 19991(;6797,19991 3651,19163 2409,16190q8300 19991Q7665 19991q6920 19815Q6043 19608q5257 19205Q4332 18732q3642 18038Q2847 17239q2409 16190);"/>
                            <Edge cubics="!2409 16190(2409,16190;666,12023 2613,9389 4695,7875q2409 16190Q1223 13353q2118 11038Q2811 9245q4695 7875);"/>
                            <Edge cubics="!4695 7875(;6589,6497 8742,6832 9530,6307q4695 7875Q5339 7406q6139 7122Q6734 6911q7527 6771Q7964 6694q8708 6580Q9281 6473q9530 6307);"/>
                            <Edge cubics="!9530 6307(;10636,5568 10444,1490 15779,1490q9530 6307Q9719 6181q9897 5888Q10025 5679q10223 5243Q10499 4634q10587 4458Q10823 3983q11069 3621Q11728 2654q12707 2139Q13942 1490q15779 1490);"/>
                          </edges>
                        </DOMShape>
                      </members>
                    </DOMGroup>
                    <DOMShape selected="true" isDrawingObject="true">
                      <matrix>
                        <Matrix a="0.0478668212890625" b="0.0386810302734375" c="-0.0386810302734375" d="0.0478668212890625" tx="30.85" ty="-47"/>
                      </matrix>
                      <fills>
                        <FillStyle index="1">
                          <LinearGradient>
                            <matrix>
                              <Matrix a="-0.2003173828125" b="-0.2203369140625" c="0.21759033203125" d="-0.197845458984375" tx="1029.15" ty="335.85"/>
                            </matrix>
                            <GradientEntry color="#FFFFFF" ratio="0"/>
                            <GradientEntry color="#FFF200" ratio="0.482352941176471"/>
                            <GradientEntry color="#ED1C24" ratio="1"/>
                          </LinearGradient>
                        </FillStyle>
                      </fills>
                      <strokes>
                        <StrokeStyle index="1">
                          <SolidStroke scaleMode="normal" caps="square" weight="12.9">
                            <fill>
                              <SolidColor color="#ED1C24"/>
                            </fill>
                          </SolidStroke>
                        </StrokeStyle>
                      </strokes>
                      <edges>
                        <Edge fillStyle0="1" strokeStyle="1" edges="
!16952 10028[17570 10028 18241 9910!18241 9910[19005 9775 19690 9508!19690 9508[21382 8850 22185 7578!22185 7578[22525 7040 22701 6279!22701 6279[22764 6003 22824 5623!22824 5623[22886 5195 22918 4991!22918 4991[23032 4257 23203 3888
!23203 3888[23441 3374 23922 3144!23922 3144[22874 3144 22175 3285!22175 3285[21424 3436 20906 3782!20906 3782[20379 4134 20005 4746!20005 4746[19641 5343 19362 6289!19362 6289[19023 7438 18870 7884!18870 7884[18630 8588 18402 8986!18402
 8986[18147 9430 17811 9674!17811 9674[17469 9922 16952 10028"/>
                        <Edge cubics="!16952 10028(;18464,10028 20998,9458 22185,7578q16952 10028Q17570 10028q18241 9910Q19005 9775q19690 9508Q21382 8850q22185 7578);"/>
                        <Edge cubics="!22185 7578(;23234,5917 22512,3818 23922,3144q22185 7578Q22525 7040q22701 6279Q22764 6003q22824 5623Q22886 5195q22918 4991Q23032 4257q23203 3888Q23441 3374q23922 3144);"/>
                        <Edge cubics="!23922 3144(;21225,3144 20097,3796 19362,6289q23922 3144Q22874 3144q22175 3285Q21424 3436q20906 3782Q20379 4134q20005 4746Q19641 5343q19362 6289);"/>
                        <Edge cubics="!19362 6289(;18626,8781 18341,9742 16952,10028q19362 6289Q19023 7438q18870 7884Q18630 8588q18402 8986Q18147 9430q17811 9674Q17469 9922q16952 10028)16952,10028;"/>
                      </edges>
                    </DOMShape>
                    <DOMShape selected="true" isDrawingObject="true">
                      <matrix>
                        <Matrix a="0.0478668212890625" b="0.0386810302734375" c="-0.0386810302734375" d="0.0478668212890625" tx="30.85" ty="-47"/>
                      </matrix>
                      <fills>
                        <FillStyle index="1">
                          <LinearGradient>
                            <matrix>
                              <Matrix a="-0.160507202148438" b="-0.1531982421875" c="0.0644683837890625" d="-0.0675506591796875" tx="846.85" ty="544.4"/>
                            </matrix>
                            <GradientEntry color="#FFFFFF" ratio="0"/>
                            <GradientEntry color="#FFF200" ratio="0.482352941176471"/>
                            <GradientEntry color="#ED1C24" ratio="1"/>
                          </LinearGradient>
                        </FillStyle>
                      </fills>
                      <edges>
                        <Edge fillStyle1="1" edges="
!14355 11796[#38DB.08 #2CE1.88 14742 11289!14742 11289[14974 11041 15252 10879!15252 10879[15872 10520 16952 10485!16952 10485[17570 10465 17926 10428!17926 10428[18348 10385 18626 10300!18626 10300[18919 10210 19135 10051!19135 10051
[19347 9894 19535 9631!19535 9631[19062 10652 18367 11016!18367 11016[18072 11169 17694 11233!17694 11233[17411 11281 16967 11291!16967 11291[16452 11293 16191 11294!16191 11294[15718 11296 15430 11326!15430 11326[#391E.68 #2C91.E1 14355
 11796"/>
                        <Edge cubics="!16952 10485(;18470,10435 19037,10326 19535,9631q16952 10485Q17570 10465q17926 10428Q18348 10385q18626 10300Q18919 10210q19135 10051Q19347 9894q19535 9631);"/>
                        <Edge cubics="!19535 9631(;18840,11133 17970,11268 16967,11291q19535 9631Q19062 10652q18367 11016Q18072 11169q17694 11233Q17411 11281q16967 11291);"/>
                        <Edge cubics="!16191 11294(;15876,11295 15622,11306 15430,11326q16191 11294Q15718 11296q15430 11326);"/>
                        <Edge cubics="!14742 11289(;14897,11124 15067,10987 15252,10879q14742 11289Q14974 11041q15252 10879)15252,10879;"/>
                        <Edge cubics="!15430 11326(15430,11326;14891,11382 14533,11539 14355,11796q15430 11326Q14622 11410q14355 11796)14355,11796;"/>
                        <Edge cubics="!14355 11796(;14488,11592 14617,11423 14742,11289q14355 11796Q14555 11490q14742 11289);"/>
                        <Edge cubics="!16967 11291(;16624,11292 16365,11293 16191,11294q16967 11291Q16452 11293q16191 11294);"/>
                        <Edge cubics="!15252 10879(;15665,10640 16232,10508 16952,10485q15252 10879Q15872 10520q16952 10485);"/>
                      </edges>
                    </DOMShape>
                    <DOMShape selected="true" isDrawingObject="true">
                      <matrix>
                        <Matrix a="0.0478668212890625" b="0.0386810302734375" c="-0.0386810302734375" d="0.0478668212890625" tx="30.85" ty="-47"/>
                      </matrix>
                      <fills>
                        <FillStyle index="1">
                          <LinearGradient>
                            <matrix>
                              <Matrix a="-0.2957763671875" b="-0.238006591796875" c="0.2000732421875" d="-0.2486572265625" tx="705.7" ty="380.65"/>
                            </matrix>
                            <GradientEntry color="#FFFFFF" ratio="0"/>
                            <GradientEntry color="#FFF200" ratio="0.482352941176471"/>
                            <GradientEntry color="#ED1C24" ratio="1"/>
                          </LinearGradient>
                        </FillStyle>
                      </fills>
                      <edges>
                        <Edge fillStyle1="1" edges="
!13020 8484[13020 7896 13494 7338!13494 7338[13943 6809 14647 6493!14647 6493[14947 6358 15359 6214!15359 6214[15784 6065 15926 6003!15926 6003[16208 5879 16433 5704!16433 5704[16696 5501 16970 5164!16970 5164[16852 6231 16355 6823!16355
 6823[16159 7056 15886 7239!15886 7239[15703 7362 15399 7511!15399 7511[15114 7651 14761 7748!14761 7748[14365 7845 14175 7894!14175 7894[13840 7980 13606 8091!13606 8091[13298 8237 13021 8484!13021 8484|13020 8484"/>
                        <Edge cubics="!13020 8484(;13020,7676 13741,6899 14647,6493q13020 8484Q13020 7896q13494 7338Q13943 6809q14647 6493);"/>
                        <Edge cubics="!14647 6493(;15733,6006 16196,6115 16970,5164q14647 6493Q14947 6358q15359 6214Q15784 6065q15926 6003Q16208 5879q16433 5704Q16696 5501q16970 5164);"/>
                        <Edge cubics="!16970 5164(;16793,6769 16030,7201 15399,7511q16970 5164Q16852 6231q16355 6823Q16159 7056q15886 7239Q15703 7362q15399 7511);"/>
                        <Edge cubics="!15399 7511(;14499,7953 13827,7765 13021,8484q15399 7511Q15114 7651q14761 7748Q14365 7845q14175 7894Q13840 7980q13606 8091Q13298 8237q13021 8484);"/>
                        <Edge cubics="!13021 8484(13021,8484;13021,8484 13020,8484 13020,8484q13021 8484 13020 8484)13020,8484;"/>
                      </edges>
                    </DOMShape>
                    <DOMShape selected="true" isDrawingObject="true">
                      <matrix>
                        <Matrix a="0.0478668212890625" b="0.0386810302734375" c="-0.0386810302734375" d="0.0478668212890625" tx="30.85" ty="-47"/>
                      </matrix>
                      <fills>
                        <FillStyle index="1">
                          <LinearGradient>
                            <matrix>
                              <Matrix a="-0.1593017578125" b="-0.1585693359375" c="0.101226806640625" d="-0.1016845703125" tx="348.05" ty="281.5"/>
                            </matrix>
                            <GradientEntry color="#FFFFFF" ratio="0"/>
                            <GradientEntry color="#FFF200" ratio="0.482352941176471"/>
                            <GradientEntry color="#ED1C24" ratio="1"/>
                          </LinearGradient>
                        </FillStyle>
                      </fills>
                      <edges>
                        <Edge fillStyle1="1" edges="
!4532 7367[4555 7271 4581 7039!4581 7039[4611 6765 4635 6627!4635 6627[4731 6078 5008 5694!5008 5694[5841 4541 8562 4384!8562 4384[8976 4384 9345 4292!9345 4292[9787 4183 9787 4008!9787 4008[9921 5929 7229 6241!7229 6241[6449 6331 5707
 6637!5707 6637[4949 6950 4532 7367"/>
                        <Edge cubics="!4532 7367(;4710,6636 4281,4631 8562,4384q4532 7367Q4555 7271q4581 7039Q4611 6765q4635 6627Q4731 6078q5008 5694Q5841 4541q8562 4384);"/>
                        <Edge cubics="!8562 4384(;9017,4384 9787,4265 9787,4008q8562 4384Q8976 4384q9345 4292Q9787 4183q9787 4008);"/>
                        <Edge cubics="!9787 4008(9787,4008;9908,5740 8256,6122 7229,6241q9787 4008Q9921 5929q7229 6241);"/>
                        <Edge cubics="!7229 6241(;6202,6359 5095,6804 4532,7367q7229 6241Q6449 6331q5707 6637Q4949 6950q4532 7367);"/>
                      </edges>
                    </DOMShape>
                    <DOMShape selected="true" isDrawingObject="true">
                      <matrix>
                        <Matrix a="0.0478668212890625" b="0.0386810302734375" c="-0.0386810302734375" d="0.0478668212890625" tx="30.85" ty="-47"/>
                      </matrix>
                      <fills>
                        <FillStyle index="1">
                          <LinearGradient>
                            <matrix>
                              <Matrix a="-0.386566162109375" b="-0.27490234375" c="0.3204345703125" d="-0.450607299804688" tx="529.35" ty="586.8"/>
                            </matrix>
                            <GradientEntry color="#FFFFFF" ratio="0"/>
                            <GradientEntry color="#FFF200" ratio="0.482352941176471"/>
                            <GradientEntry color="#ED1C24" ratio="1"/>
                          </LinearGradient>
                        </FillStyle>
                      </fills>
                      <edges>
                        <Edge fillStyle0="1" edges="
!13324 2408[#330F.5 #A02.44 12775 2797!12775 2797[12293 3179 11846 3655!11846 3655[11373 4159 11072 4629!11072 4629[10740 5147 10681 5529!10681 5529[10580 6185 9909 6634!9909 6634[9396 6977 8356 7301!8356 7301[8107 7379 7440 7570!7440
 7570[6845 7741 6512 7850!6512 7850[5448 8197 4864 8600!4864 8600[3648 9439 2981 10719!2981 10719[2348 11935 2321 13322!2321 13322[2293 14701 2870 15944!2870 15944[3472 17243 4616 18125!4616 18125[6420 19517 8597 19498!8597 19498[9379
 19492 10161 19300!10161 19300[10709 19166 11192 18959!11192 18959[11513 18821 11947 18504!11947 18504[12477 18115 12956 17605!12956 17605[14246 16231 14704 14493!14704 14493[14794 14151 15107 13807!15107 13807[15374 13515 15772 13251
!15772 13251[16110 13027 16455 12879!16455 12879[#417A.18 #31CB.4 16908 12743!16908 12743[#40A5.35 #31C8.74 15946 12857!15946 12857[15263 12985 14633 13193!14633 13193[13889 13439 13407 13742!13407 13742[12841 14096 12697 14493!12697
 14493[12697 13814 12715 13495!12715 13495[12744 12970 12839 12569!12839 12569[13068 11600 13829 10838!13829 10838[14170 10497 14785 10072!14785 10072[14826 10044 15300 9723!15300 9723[15610 9513 15803 9371!15803 9371[16359 8959 16658
 8579!16658 8579[17033 8102 17123 7544!17123 7544[17049 7772 16589 8089!16589 8089[16148 8393 15426 8729!15426 8729[13877 9449 12027 9912!12027 9912[10483 10298 9441 10877!9441 10877[8920 11167 8708 11379!8708 11379[8859 10908 9217 10497
!9217 10497[9499 10173 9984 9812!9984 9812[10265 9602 10854 9197!10854 9197[11370 8828 11671 8527!11671 8527[12392 7806 12720 6470!12720 6470[12954 5517 12954 4456!12954 4456[12954 3534 13091 2964!13091 2964[#337D.48 #A1B.BC 13324 2408"/>
                        <Edge fillStyle1="1" edges="
!13324 2408[#348F.01 2243 13630 2243!13630 2243[#34AD.FA #904.F6 13324 2408"/>
                        <Edge cubics="!4864 8600(;1533,10898 1495,15718 4616,18125q4864 8600Q3648 9439q2981 10719Q2348 11935q2321 13322Q2293 14701q2870 15944Q3472 17243q4616 18125)4616,18125;"/>
                        <Edge cubics="!4616 18125(;7401,20274 10255,19360 11192,18959q4616 18125Q6420 19517q8597 19498Q9379 19492q10161 19300Q10709 19166q11192 18959);"/>
                        <Edge cubics="!11192 18959(;11913,18650 14005,17146 14704,14493q11192 18959Q11513 18821q11947 18504Q12477 18115q12956 17605Q14246 16231q14704 14493)14704,14493;"/>
                        <Edge cubics="!12697 14493(;12697,13103 12697,11971 13829,10838q12697 14493Q12697 13814q12715 13495Q12744 12970q12839 12569Q13068 11600q13829 10838);"/>
                        <Edge cubics="!13829 10838(;14961,9706 16863,9155 17123,7544q13829 10838Q14170 10497q14785 10072Q14826 10044q15300 9723Q15610 9513q15803 9371Q16359 8959q16658 8579Q17033 8102q17123 7544);"/>
                        <Edge cubics="!17123 7544(;16922,8164 14498,9294 12027,9912q17123 7544Q17049 7772q16589 8089Q16148 8393q15426 8729Q13877 9449q12027 9912);"/>
                        <Edge cubics="!12027 9912(;9557,10530 8708,11379 8708,11379q12027 9912Q10483 10298q9441 10877Q8920 11167q8708 11379);"/>
                        <Edge cubics="!8708 11379(;9145,10015 10685,9514 11671,8527q8708 11379Q8859 10908q9217 10497Q9499 10173q9984 9812Q10265 9602q10854 9197Q11370 8828q11671 8527)11671,8527;"/>
                        <Edge cubics="!11671 8527(;12758,7440 12954,5486 12954,4456q11671 8527Q12392 7806q12720 6470Q12954 5517q12954 4456);"/>
                        <Edge cubics="!12954 4456(;12954,3660 13038,2771 13324,2408q12954 4456Q12954 3534q13091 2964Q13181 2588q13324 2408);"/>
                        <Edge cubics="!13324 2408(;13408,2304 13509,2243 13630,2243q13324 2408Q13455 2243q13630 2243);"/>
                        <Edge cubics="!10681 5529(;10388,7437 6714,7323 4864,8600q10681 5529Q10580 6185q9909 6634Q9396 6977q8356 7301Q8107 7379q7440 7570Q6845 7741q6512 7850Q5448 8197q4864 8600)4864,8600;"/>
                        <Edge cubics="!13630 2243(;13534,2287 13432,2342 13324,2408q13630 2243Q13486 2309q13324 2408);"/>
                        <Edge cubics="!15946 12857(;15491,12942 15053,13054 14633,13193q15946 12857Q15263 12985q14633 13193)14633,13193;"/>
                        <Edge cubics="!15107 13807(;15285,13612 15507,13427 15772,13251q15107 13807Q15374 13515q15772 13251);"/>
                        <Edge cubics="!14633 13193(;14137,13357 13728,13540 13407,13742q14633 13193Q13889 13439q13407 13742);"/>
                        <Edge cubics="!14704 14493(;14764,14265 14898,14036 15107,13807q14704 14493Q14794 14151q15107 13807);"/>
                        <Edge cubics="!16455 12879(;16660,12791 16811,12746 16908,12743q16455 12879Q16762 12747q16908 12743);"/>
                        <Edge cubics="!16908 12743(16908,12743;16669,12744 16348,12782 15946,12857q16908 12743Q16549 12744q15946 12857)15946,12857;"/>
                        <Edge cubics="!15772 13251(;15997,13102 16225,12978 16455,12879q15772 13251Q16110 13027q16455 12879);"/>
                        <Edge cubics="!12775 2797(;12454,3052 12144,3338 11846,3655q12775 2797Q12293 3179q11846 3655)11846,3655;"/>
                        <Edge cubics="!11072 4629(;10851,4974 10720,5274 10681,5529q11072 4629Q10740 5147q10681 5529);"/>
                        <Edge cubics="!11846 3655(;11531,3991 11273,4316 11072,4629q11846 3655Q11373 4159q11072 4629);"/>
                        <Edge cubics="!13324 2408(;13155,2511 12972,2640 12775,2797q13324 2408Q13071 2562q12775 2797);"/>
                        <Edge cubics="!13407 13742(13407,13742;13030,13978 12793,14228 12697,14493q13407 13742Q12841 14096q12697 14493);"/>
                      </edges>
                    </DOMShape>
                    <DOMShape selected="true" isDrawingObject="true">
                      <matrix>
                        <Matrix a="0.0478668212890625" b="0.0386810302734375" c="-0.0386810302734375" d="0.0478668212890625" tx="30.85" ty="-47"/>
                      </matrix>
                      <fills>
                        <FillStyle index="1">
                          <LinearGradient>
                            <matrix>
                              <Matrix a="-0.120697021484375" b="-0.262847900390625" c="0.16143798828125" d="-0.074127197265625" tx="1023.05" ty="140.95"/>
                            </matrix>
                            <GradientEntry color="#FFFFFF" ratio="0"/>
                            <GradientEntry color="#FFF200" ratio="0.482352941176471"/>
                            <GradientEntry color="#ED1C24" ratio="1"/>
                          </LinearGradient>
                        </FillStyle>
                      </fills>
                      <strokes>
                        <StrokeStyle index="1">
                          <SolidStroke scaleMode="normal" caps="square" weight="9.9">
                            <fill>
                              <SolidColor color="#ED1C24"/>
                            </fill>
                          </SolidStroke>
                        </StrokeStyle>
                      </strokes>
                      <edges>
                        <Edge fillStyle0="1" strokeStyle="1" edges="
!17586 4550[#4688.09 #11F6.D1 18597 4503!18597 4503[19131 4407 19638 4188!19638 4188[20159 3962 20561 3644!20561 3644[20987 3307 21218 2913!21218 2913[21650 2176 22436 1542!22436 1542[22751 1289 23028 1133!23028 1133[#5AF9.D8 #3DA.54
 23412 984!23412 984[#568D.7A #3D8.A5 21161 1407!21161 1407[20399 1730 20014 2174!20014 2174[19910 2293 19562 2733!19562 2733[19230 3153 19003 3408!19003 3408[#4751.FE #1094.E3 17586 4550"/>
                        <Edge fillStyle1="1" strokeStyle="1" edges="
!17586 4550[#44B0.E5 #11C6.98 17584 4551!17584 4551|17584 4550!17584 4550[#44B0.E6 #11C6.18 17586 4550"/>
                        <Edge cubics="!17584 4551(17584,4551;17584,4551 17584,4550 17584,4550p17584 4551 17584 4550);"/>
                        <Edge cubics="!23028 1133(;23203,1035 23331,985 23412,984q23028 1133Q23290 986q23412 984);"/>
                        <Edge cubics="!20014 2174(;19945,2253 19794,2440 19562,2733q20014 2174Q19910 2293q19562 2733)19562,2733;"/>
                        <Edge cubics="!21161 1407(;20653,1622 20271,1878 20014,2174q21161 1407Q20399 1730q20014 2174)20014,2174;"/>
                        <Edge cubics="!21218 2913(;21506,2422 21912,1965 22436,1542q21218 2913Q21650 2176q22436 1542);"/>
                        <Edge cubics="!20561 3644(;20845,3419 21064,3176 21218,2913q20561 3644Q20987 3307q21218 2913);"/>
                        <Edge cubics="!23412 984(;22575,985 21825,1126 21161,1407q23412 984Q22157 985q21161 1407);"/>
                        <Edge cubics="!22436 1542(;22646,1373 22843,1237 23028,1133q22436 1542Q22751 1289q23028 1133);"/>
                        <Edge cubics="!19638 4188(;19985,4037 20293,3856 20561,3644q19638 4188Q20159 3962q20561 3644);"/>
                        <Edge cubics="!17586 4550(17586,4550;17585,4551 17585,4551 17584,4551p17586 4550Q17585 4551q17584 4551)17584,4551;"/>
                        <Edge cubics="!17584 4550(17584,4550;17585,4550 17585,4550 17586,4550q17584 4550Q17585 4550p17586 4550)17586,4550;"/>
                        <Edge cubics="!17586 4550(;17899,4583 18236,4567 18597,4503p17586 4550Q18056 4599q18597 4503);"/>
                        <Edge cubics="!19003 3408(;18506,3966 18034,4347 17586,4550q19003 3408Q18258 4245p17586 4550)17586,4550;"/>
                        <Edge cubics="!19562 2733(;19341,3013 19154,3238 19003,3408q19562 2733Q19230 3153q19003 3408);"/>
                        <Edge cubics="!18597 4503(;18953,4439 19300,4334 19638,4188q18597 4503Q19131 4407q19638 4188)19638,4188;"/>
                      </edges>
                    </DOMShape>
                  </members>
                </DOMGroup>
              </elements>
            </DOMFrame>
          </frames>
        </DOMLayer>
      </layers>
    </DOMTimeline>
  </timeline>
</DOMSymbolItem>